piworld/__init__.py
piworld/_core.py
piworld-0.2.0.dist-info/licenses/LICENSE.txt
piworld-0.2.0.dist-info/METADATA
piworld-0.2.0.dist-info/WHEEL
piworld-0.2.0.dist-info/top_level.txt
piworld-0.2.0.dist-info/RECORD
