Metadata-Version: 2.4
Name: piworld
Version: 0.2.0
Summary: A small library for pi related functions
Author: seif-kz
License: MIT
Keywords: pi
License-File: LICENSE.txt
Dynamic: license-file
